AUTHORS.rst
CONTRIBUTING.rst
HISTORY.rst
LICENSE
MANIFEST.in
README.rst
setup.cfg
setup.py
degreedClient/__init__.py
degreedClient/articles.py
degreedClient/books.py
degreedClient/certifiable_skills.py
degreedClient/cli.py
degreedClient/client.py
degreedClient/compatibility.py
degreedClient/completions.py
degreedClient/content.py
degreedClient/courses.py
degreedClient/exceptions.py
degreedClient/groups.py
degreedClient/logins.py
degreedClient/pathways.py
degreedClient/providers.py
degreedClient/recommendations.py
degreedClient/required_learnings.py
degreedClient/search_terms.py
degreedClient/skills_plan.py
degreedClient/skills_ratings.py
degreedClient/the_views.py
degreedClient/user_followers.py
degreedClient/user_skills.py
degreedClient/users.py
degreedClient/videos.py
degreedClient/models/attribute.py
degreedClient/models/certifiable_skill.py
degreedClient/models/completion.py
degreedClient/models/content.py
degreedClient/models/group.py
degreedClient/models/login.py
degreedClient/models/pathway.py
degreedClient/models/provider.py
degreedClient/models/recommendation.py
degreedClient/models/required_learning.py
degreedClient/models/search_term.py
degreedClient/models/skill_plan.py
degreedClient/models/skills_rating.py
degreedClient/models/the_view.py
degreedClient/models/user.py
degreedClient/models/user_follower.py
degreedClient/models/user_skill.py
degreed_client.egg-info/PKG-INFO
degreed_client.egg-info/SOURCES.txt
degreed_client.egg-info/dependency_links.txt
degreed_client.egg-info/entry_points.txt
degreed_client.egg-info/not-zip-safe
degreed_client.egg-info/requires.txt
degreed_client.egg-info/top_level.txt
docs/Makefile
docs/api.rst
docs/authors.rst
docs/conf.py
docs/contributing.rst
docs/history.rst
docs/index.rst
docs/installation.rst
docs/make.bat
docs/readme.rst
docs/usage.rst
docs/_build/html/_static/ajax-loader.gif
docs/_build/html/_static/comment-bright.png
docs/_build/html/_static/comment-close.png
docs/_build/html/_static/comment.png
docs/_build/html/_static/down-pressed.png
docs/_build/html/_static/down.png
docs/_build/html/_static/file.png
docs/_build/html/_static/minus.png
docs/_build/html/_static/plus.png
docs/_build/html/_static/up-pressed.png
docs/_build/html/_static/up.png
tests/__init__.py
