Metadata-Version: 1.1
Name: degreed-client
Version: 2.2.2
Summary: The Degreed python package to leverage and connect to the Degreed API from python 3.
Home-page: https://github.com/Rmaravanyika/degreedClient
Author: Ronald Maravanyika
Author-email: rmaravanyika@gmail.com
License: Apache Software License 2.0
Keywords: degreedClient
Platform: UNKNOWN
Classifier: Development Status :: 2 - Pre-Alpha
Classifier: Intended Audience :: Developers
Classifier: License :: OSI Approved :: Apache Software License
Classifier: Natural Language :: English
Classifier: Programming Language :: Python :: 3.6
Classifier: Programming Language :: Python :: 3.7
